[
  {
    "id": "936826a7-1f21-43c6-bb4d-617c8ad52c06",
    "data": [
      {
        "text": "claro que sí",
        "userDefined": false
      }
    ],
    "isTemplate": false,
    "count": 0,
    "updated": 1497432757
  },
  {
    "id": "16c45c29-88a5-43ea-a52f-dc990e3d4011",
    "data": [
      {
        "text": "si me lo han dado",
        "userDefined": false
      }
    ],
    "isTemplate": false,
    "count": 0,
    "updated": 1497432757
  },
  {
    "id": "5bd40cf4-35f8-4996-bc5d-8d4edf44b5e3",
    "data": [
      {
        "text": "si lo tengo",
        "userDefined": false
      }
    ],
    "isTemplate": false,
    "count": 0,
    "updated": 1497432757
  },
  {
    "id": "390aff06-b7e5-401e-aff6-67b229f7275e",
    "data": [
      {
        "text": "sí",
        "userDefined": false
      }
    ],
    "isTemplate": false,
    "count": 0,
    "updated": 1497432757
  },
  {
    "id": "f40ae0e6-a032-4d73-a702-d219a7723d08",
    "data": [
      {
        "text": "correcto",
        "userDefined": false
      }
    ],
    "isTemplate": false,
    "count": 0,
    "updated": 1497432757
  },
  {
    "id": "1b241a13-10e0-409d-869c-9c79c992e4cf",
    "data": [
      {
        "text": "por supuesto",
        "userDefined": false
      }
    ],
    "isTemplate": false,
    "count": 0,
    "updated": 1497432757
  },
  {
    "id": "9f289a55-2bfd-4d4d-a357-1db556b04aeb",
    "data": [
      {
        "text": "creo que si",
        "userDefined": false
      }
    ],
    "isTemplate": false,
    "count": 0,
    "updated": 1497432757
  },
  {
    "id": "8ec22a1a-517f-49dd-a72a-4abaa2e984ae",
    "data": [
      {
        "text": "si",
        "userDefined": false
      }
    ],
    "isTemplate": false,
    "count": 0,
    "updated": 1497432757
  }
]